<?xml version="1.0" encoding="UTF-8" ?>
<!DOCTYPE mapper PUBLIC "-//mybatis.org//DTD Mapper 3.0//EN" "http://mybatis.org/dtd/mybatis-3-mapper.dtd" >
<mapper namespace="com.clesun.web.skyland.dao.PlantrecordMapper" >
  <resultMap id="BaseResultMap" type="com.clesun.web.skyland.entity.Plantrecord" >
    <!--
      WARNING - @mbggenerated
      This element is automatically generated by MyBatis Generator, do not modify.
      This element was generated on Tue Jan 08 09:35:44 CST 2019.
    -->
    <result column="bh" property="bh" jdbcType="VARCHAR" />
    <result column="plantbh" property="plantbh" jdbcType="VARCHAR" />
    <result column="parcelbh" property="parcelbh" jdbcType="VARCHAR" />
    <result column="area" property="area" jdbcType="VARCHAR" />
    <result column="sdate" property="sdate" jdbcType="DATE" />
    <result column="edate" property="edate" jdbcType="DATE" />
  </resultMap>
  <sql id="Example_Where_Clause" >
    <!--
      WARNING - @mbggenerated
      This element is automatically generated by MyBatis Generator, do not modify.
      This element was generated on Tue Jan 08 09:35:44 CST 2019.
    -->
    <where >
      <foreach collection="oredCriteria" item="criteria" separator="or" >
        <if test="criteria.valid" >
          <trim prefix="(" suffix=")" prefixOverrides="and" >
            <foreach collection="criteria.criteria" item="criterion" >
              <choose >
                <when test="criterion.noValue" >
                  and ${criterion.condition}
                </when>
                <when test="criterion.singleValue" >
                  and ${criterion.condition} #{criterion.value}
                </when>
                <when test="criterion.betweenValue" >
                  and ${criterion.condition} #{criterion.value} and #{criterion.secondValue}
                </when>
                <when test="criterion.listValue" >
                  and ${criterion.condition}
                  <foreach collection="criterion.value" item="listItem" open="(" close=")" separator="," >
                    #{listItem}
                  </foreach>
                </when>
              </choose>
            </foreach>
          </trim>
        </if>
      </foreach>
    </where>
  </sql>
  <sql id="Update_By_Example_Where_Clause" >
    <!--
      WARNING - @mbggenerated
      This element is automatically generated by MyBatis Generator, do not modify.
      This element was generated on Tue Jan 08 09:35:44 CST 2019.
    -->
    <where >
      <foreach collection="example.oredCriteria" item="criteria" separator="or" >
        <if test="criteria.valid" >
          <trim prefix="(" suffix=")" prefixOverrides="and" >
            <foreach collection="criteria.criteria" item="criterion" >
              <choose >
                <when test="criterion.noValue" >
                  and ${criterion.condition}
                </when>
                <when test="criterion.singleValue" >
                  and ${criterion.condition} #{criterion.value}
                </when>
                <when test="criterion.betweenValue" >
                  and ${criterion.condition} #{criterion.value} and #{criterion.secondValue}
                </when>
                <when test="criterion.listValue" >
                  and ${criterion.condition}
                  <foreach collection="criterion.value" item="listItem" open="(" close=")" separator="," >
                    #{listItem}
                  </foreach>
                </when>
              </choose>
            </foreach>
          </trim>
        </if>
      </foreach>
    </where>
  </sql>
  <sql id="Base_Column_List" >
    <!--
      WARNING - @mbggenerated
      This element is automatically generated by MyBatis Generator, do not modify.
      This element was generated on Tue Jan 08 09:35:44 CST 2019.
    -->
    bh, plantbh, parcelbh, area, sdate, edate
  </sql>
  <select id="selectByExample" resultMap="BaseResultMap" parameterType="com.clesun.web.skyland.entity.PlantrecordExample" >
    <!--
      WARNING - @mbggenerated
      This element is automatically generated by MyBatis Generator, do not modify.
      This element was generated on Tue Jan 08 09:35:44 CST 2019.
    -->
    select
    <if test="distinct" >
      distinct
    </if>
    <include refid="Base_Column_List" />
    from PLANTRECORD
    <if test="_parameter != null" >
      <include refid="Example_Where_Clause" />
    </if>
    <if test="orderByClause != null" >
      order by ${orderByClause}
    </if>
    <if test="limit > 0" >
      limit ${offset},${limit}
    </if>
  </select>
  <delete id="deleteByExample" parameterType="com.clesun.web.skyland.entity.PlantrecordExample" >
    <!--
      WARNING - @mbggenerated
      This element is automatically generated by MyBatis Generator, do not modify.
      This element was generated on Tue Jan 08 09:35:44 CST 2019.
    -->
    delete from PLANTRECORD
    <if test="_parameter != null" >
      <include refid="Example_Where_Clause" />
    </if>
  </delete>
  <insert id="insert" parameterType="com.clesun.web.skyland.entity.Plantrecord" >
    <!--
      WARNING - @mbggenerated
      This element is automatically generated by MyBatis Generator, do not modify.
      This element was generated on Tue Jan 08 09:35:44 CST 2019.
    -->
    insert into PLANTRECORD (bh, plantbh, parcelbh, 
      area, sdate, edate)
    values (#{bh,jdbcType=VARCHAR}, #{plantbh,jdbcType=VARCHAR}, #{parcelbh,jdbcType=VARCHAR}, 
      #{area,jdbcType=VARCHAR}, #{sdate,jdbcType=DATE}, #{edate,jdbcType=DATE})
  </insert>
  <insert id="insertSelective" parameterType="com.clesun.web.skyland.entity.Plantrecord" >
    <!--
      WARNING - @mbggenerated
      This element is automatically generated by MyBatis Generator, do not modify.
      This element was generated on Tue Jan 08 09:35:44 CST 2019.
    -->
    insert into PLANTRECORD
    <trim prefix="(" suffix=")" suffixOverrides="," >
      <if test="bh != null" >
        bh,
      </if>
      <if test="plantbh != null" >
        plantbh,
      </if>
      <if test="parcelbh != null" >
        parcelbh,
      </if>
      <if test="area != null" >
        area,
      </if>
      <if test="sdate != null" >
        sdate,
      </if>
      <if test="edate != null" >
        edate,
      </if>
    </trim>
    <trim prefix="values (" suffix=")" suffixOverrides="," >
      <if test="bh != null" >
        #{bh,jdbcType=VARCHAR},
      </if>
      <if test="plantbh != null" >
        #{plantbh,jdbcType=VARCHAR},
      </if>
      <if test="parcelbh != null" >
        #{parcelbh,jdbcType=VARCHAR},
      </if>
      <if test="area != null" >
        #{area,jdbcType=VARCHAR},
      </if>
      <if test="sdate != null" >
        #{sdate,jdbcType=DATE},
      </if>
      <if test="edate != null" >
        #{edate,jdbcType=DATE},
      </if>
    </trim>
  </insert>
  <select id="countByExample" parameterType="com.clesun.web.skyland.entity.PlantrecordExample" resultType="java.lang.Integer" >
    <!--
      WARNING - @mbggenerated
      This element is automatically generated by MyBatis Generator, do not modify.
      This element was generated on Tue Jan 08 09:35:44 CST 2019.
    -->
    select count(*) from PLANTRECORD
    <if test="_parameter != null" >
      <include refid="Example_Where_Clause" />
    </if>
  </select>
  <update id="updateByExampleSelective" parameterType="map" >
    <!--
      WARNING - @mbggenerated
      This element is automatically generated by MyBatis Generator, do not modify.
      This element was generated on Tue Jan 08 09:35:44 CST 2019.
    -->
    update PLANTRECORD
    <set >
      <if test="record.bh != null" >
        bh = #{record.bh,jdbcType=VARCHAR},
      </if>
      <if test="record.plantbh != null" >
        plantbh = #{record.plantbh,jdbcType=VARCHAR},
      </if>
      <if test="record.parcelbh != null" >
        parcelbh = #{record.parcelbh,jdbcType=VARCHAR},
      </if>
      <if test="record.area != null" >
        area = #{record.area,jdbcType=VARCHAR},
      </if>
      <if test="record.sdate != null" >
        sdate = #{record.sdate,jdbcType=DATE},
      </if>
      <if test="record.edate != null" >
        edate = #{record.edate,jdbcType=DATE},
      </if>
    </set>
    <if test="_parameter != null" >
      <include refid="Update_By_Example_Where_Clause" />
    </if>
  </update>
  <update id="updateByExample" parameterType="map" >
    <!--
      WARNING - @mbggenerated
      This element is automatically generated by MyBatis Generator, do not modify.
      This element was generated on Tue Jan 08 09:35:44 CST 2019.
    -->
    update PLANTRECORD
    set bh = #{record.bh,jdbcType=VARCHAR},
      plantbh = #{record.plantbh,jdbcType=VARCHAR},
      parcelbh = #{record.parcelbh,jdbcType=VARCHAR},
      area = #{record.area,jdbcType=VARCHAR},
      sdate = #{record.sdate,jdbcType=DATE},
      edate = #{record.edate,jdbcType=DATE}
    <if test="_parameter != null" >
      <include refid="Update_By_Example_Where_Clause" />
    </if>
  </update>
</mapper>